pyretras/__init__.py
pyretras/pyretras.py
pyretras/chemicalsystem/__init__.py
pyretras/chemicalsystem/chemicalsystem.py
pyretras/dataloaders/__init__.py
pyretras/dataloaders/chemloader.py
pyretras/dataloaders/dbaseloader.py
pyretras/dataloaders/heattranloader.py
pyretras/dataloaders/tranloader.py
pyretras/grids/__init__.py
pyretras/grids/grid.py
pyretras/heattransport/__init__.py
pyretras/heattransport/heattran.py
pyretras/solutetransport/__init__.py
pyretras/solutetransport/solutetransport.py
pyretras/utilities/__init__.py
pyretras/utilities/loadcoreoutput.py
pyretras/waterflow/__init__.py
pyretras/waterflow/confinedflow.py
pyretras/waterflow/unsatflow.py
pyretras-0.1.0.dist-info/licenses/LICENSE
pyretras-0.1.0.dist-info/METADATA
pyretras-0.1.0.dist-info/WHEEL
pyretras-0.1.0.dist-info/top_level.txt
pyretras-0.1.0.dist-info/RECORD
