Metadata-Version: 2.4
Name: pyretras
Version: 0.1.0
Summary: Python code to simulate solute transport in porous media coupled with geochemical reactions
Author-email: Changbing Yang <yangcb@gmail.com>
License: MIT License
Requires-Python: >=3.7
License-File: LICENSE
Requires-Dist: numpy
Requires-Dist: pandas
Requires-Dist: matplotlib
Requires-Dist: scipy
Dynamic: license-file
